json_cfdi/__init__.py
json_cfdi/handlers.py
json_cfdi/wrappers/__init__.py
json_cfdi/wrappers/cfdi33.py
json_cfdi/wrappers/cfdi40.py
json_cfdi/wrappers/locations.py
json_cfdi/wrappers/nomina12.py
json_cfdi/wrappers/schemas.py
json_cfdi/wrappers/timbreFiscalDigital11.py
json_cfdi/wrappers/utils.py
json_cfdi/wrappers/xsds/__init__.py
json_cfdi/wrappers/xsds/acreditamientoIEPS10.xsd
json_cfdi/wrappers/xsds/aerolineas10.xsd
json_cfdi/wrappers/xsds/cartaPorte10.xsd
json_cfdi/wrappers/xsds/cartaPorte20.xsd
json_cfdi/wrappers/xsds/certificadodedestruccion10.xsd
json_cfdi/wrappers/xsds/cfdv33.xsd
json_cfdi/wrappers/xsds/cfdv40.xsd
json_cfdi/wrappers/xsds/comercioExterior11.xsd
json_cfdi/wrappers/xsds/consumodeCombustibles11.xsd
json_cfdi/wrappers/xsds/divisas10.xsd
json_cfdi/wrappers/xsds/donat11.xsd
json_cfdi/wrappers/xsds/ecc12.xsd
json_cfdi/wrappers/xsds/gastosHidrocarburos10.xsd
json_cfdi/wrappers/xsds/iedu.xsd
json_cfdi/wrappers/xsds/implocal.xsd
json_cfdi/wrappers/xsds/ine11.xsd
json_cfdi/wrappers/xsds/leyendasFisc.xsd
json_cfdi/wrappers/xsds/nomina11.xsd
json_cfdi/wrappers/xsds/nomina12.xsd
json_cfdi/wrappers/xsds/nomina12b.xsd
json_cfdi/wrappers/xsds/notariospublicos.xsd
json_cfdi/wrappers/xsds/obrasarteantiguedades.xsd
json_cfdi/wrappers/xsds/pagoenespecie.xsd
json_cfdi/wrappers/xsds/pagos10.xsd
json_cfdi/wrappers/xsds/pagos20.xsd
json_cfdi/wrappers/xsds/pfic.xsd
json_cfdi/wrappers/xsds/servicioparcialconstruccion10.xsd
json_cfdi/wrappers/xsds/timbreFiscalDigital10.xsd
json_cfdi/wrappers/xsds/timbreFiscalDigital11.xsd
tests/__init__.py
tests/test_configurations.py
tests/assets/__init__.py
tests/test_cfdi33/__init__.py
tests/test_cfdi33/test_cfdi33.py
tests/test_cfdi33/test_complemento/__init__.py
tests/test_cfdi33/test_complemento/test_nomina12.py
tests/test_cfdi33/test_complemento/test_timbre_fiscal_digital.py
tests/test_cfdi40/__init__.py
tests/test_cfdi40/test_cfdi40.py
tests/test_cfdi40/test_complemento/__init__.py
json_cfdi-0.2.dist-info/LICENCE
json_cfdi-0.2.dist-info/METADATA
json_cfdi-0.2.dist-info/WHEEL
json_cfdi-0.2.dist-info/top_level.txt
json_cfdi-0.2.dist-info/RECORD
