Metadata-Version: 2.1
Name: json-cfdi
Version: 0.2
Summary: CFDI's expedidos por el SAT (México) de XML a objetos python
Home-page: https://gitlab.com/workyhr/json_cfdi/
Author: Worky HR
Author-email: opensource@worky.mx
Classifier: Programming Language :: Python
Classifier: Programming Language :: Python :: 3
Classifier: Development Status :: 5 - Production/Stable
Classifier: License :: OSI Approved :: MIT License
Classifier: Operating System :: OS Independent
Classifier: Intended Audience :: Developers
Classifier: Natural Language :: Spanish
Classifier: Topic :: Software Development
Requires-Python: >=3
License-File: LICENCE
Requires-Dist: xmlschema (>=1.11)
Requires-Dist: jsonpickle (>=2.0)
